arkid/.dockerignore
arkid/.gitignore
arkid/.pre-commit-config.yaml
arkid/.pylintrc
arkid/.style.yapf
arkid/Dockerfile
arkid/Makefile
arkid/Pipfile
arkid/Pipfile.lock
arkid/README.md
arkid/__init__.py
arkid/celery_app.py
arkid/manage.py
arkid/requirements-dev.txt
arkid/requirements.txt
arkid/supervisord.conf
arkid/uwsgi.ini
arkid/common/__init__.py
arkid/common/excel_utils.py
arkid/common/minio_utils.py
arkid/common/redis_utils.py
arkid/common/setup_utils.py
arkid/common/Email/__init__.py
arkid/common/Email/email_manager.py
arkid/common/django/__init__.py
arkid/common/django/middleware.py
arkid/common/django/model.py
arkid/common/django/drf/__init__.py
arkid/common/django/drf/client.py
arkid/common/django/drf/paginator.py
arkid/common/django/drf/serializer.py
arkid/common/django/drf/views.py
arkid/common/redisdb/__init__.py
arkid/common/redisdb/connection.py
arkid/common/redisdb/wrapper.py
arkid/common/sms/.__init__.py
arkid/common/sms/aliyun/__init__.py
arkid/common/sms/aliyun/constants.py
arkid/common/sms/aliyun/sms_manager.py
arkid/common/sms/aliyun/request/__init__.py
arkid/common/sms/aliyun/request/v20170525/QueryInterSmsIsoInfoRequest.py
arkid/common/sms/aliyun/request/v20170525/QuerySendDetailsRequest.py
arkid/common/sms/aliyun/request/v20170525/SendBatchSmsRequest.py
arkid/common/sms/aliyun/request/v20170525/SendInterSmsRequest.py
arkid/common/sms/aliyun/request/v20170525/SendSmsRequest.py
arkid/common/sms/aliyun/request/v20170525/__init__.py
arkid/common/sms/vendor/CCPRestSDK.py
arkid/common/sms/vendor/__init__.py
arkid/common/sms/vendor/xmltojson.py
arkid/common/sms/zzb/__init__.py
arkid/common/sms/zzb/sms_manager.py
arkid/db/.gitkeep
arkid/devops/jenkinsfile.build
arkid/devops/jenkinsfile.deploy
arkid/devops/jenkinsfile.release
arkid/devops/jenkinsfile.status
arkid/devops/pip.conf
arkid/djangosaml2idp/__init__.py
arkid/djangosaml2idp/error_views.py
arkid/djangosaml2idp/idpsettings.py
arkid/djangosaml2idp/idpview.py
arkid/djangosaml2idp/processors.py
django_arkid-0.1.3.dist-info/LICENSE.md
django_arkid-0.1.3.dist-info/METADATA
django_arkid-0.1.3.dist-info/WHEEL
django_arkid-0.1.3.dist-info/dependency_links.txt
django_arkid-0.1.3.dist-info/top_level.txt
django_arkid-0.1.3.dist-info/zip-safe
django_arkid-0.1.3.dist-info/RECORD
