Metadata-Version: 2.1
Name: django-arkid
Version: 0.1.3
Summary: ArkID是全新一代企业单点登录解决方案, 彻底告别企业内多系统多账号的烦恼, 节省管理成本, 自带功能全面的WEB管理界面，提升管理效率。
Home-page: https://github.com/longguikeji/arkid-core
Author: longguikeji
Author-email: rr97390483@dingtalk.com
License: UNKNOWN
Download-URL: https://github.com/longguikeji/arkid-core
Keywords: django LDAP OAuth OpenID SAML SSO HTTP API
Platform: UNKNOWN
Classifier: Development Status :: 5 - Production/Stable
Classifier: Intended Audience :: Developers
Classifier: Topic :: Software Development :: Libraries :: Python Modules
Classifier: Environment :: Web Environment
Classifier: Topic :: Internet
Classifier: License :: OSI Approved :: GNU General Public License (GPL)
Classifier: Operating System :: OS Independent
Classifier: Programming Language :: Python
Classifier: Programming Language :: Python :: 3.6
Classifier: Framework :: Django :: 2.0
Classifier: Framework :: Django :: 3.0
Requires-Dist: django (==2.2.10)
Requires-Dist: djangorestframework (==3.10.2)
Requires-Dist: django-cors-headers (==2.5.3)
Requires-Dist: celery (==4.2.1)
Requires-Dist: coreapi (==2.3.3)
Requires-Dist: django-celery-results (==1.0.1)
Requires-Dist: django-celery-beat (==1.1.1)
Requires-Dist: pylint
Requires-Dist: rules (==2.0)
Requires-Dist: ldap3 (==2.5.2)
Requires-Dist: passlib
Requires-Dist: pypinyin
Requires-Dist: django-oauth-toolkit (==1.2.0)
Requires-Dist: django-cors-middleware (==1.4.0)
Requires-Dist: redis (==3.2.0)
Requires-Dist: django-simple-captcha (==0.5.12)
Requires-Dist: aliyun-python-sdk-core-v3 (==2.8.6)
Requires-Dist: sqlparse
Requires-Dist: kubernetes (==10.0.0)
Requires-Dist: django-jsonfield (==1.2.0)
Requires-Dist: minio (==4.0.18)
Requires-Dist: cryptography (==2.8)
Requires-Dist: django-redis (==4.10.0)
Requires-Dist: alipay-sdk-python (==3.3.202)
Requires-Dist: pysaml2 (==4.9.0)
Requires-Dist: mako (==1.1.0)
Requires-Dist: pyasn1 (==0.4.8)
Requires-Dist: repoze-who (==2.3)
Requires-Dist: cherrypy (==18.4.0)
Requires-Dist: pyjwkest
